{
    "ff_file":{
        "et": "/data/higgs/Jet2TauFakesFiles/SM2016_ML/180504_tight/et/fakeFactors_20180412_tight.root",
        "mt": "/data/higgs/Jet2TauFakesFiles/SM2016_ML/180504_tight/mt/fakeFactors_20180406_tight.root",
        "tt": "/data/higgs/Jet2TauFakesFiles/SM2016_ML/180504_tight/tt/fakeFactors_tt_inclusive.root"
    },
   "inputs":{
        "et": {"vars":["pt_2","decayMode_2","njets","m_vis","mt_1","iso_1"],
               "frac":["QCD","W","TT"]
        },
        "mt": {"vars":["pt_2","decayMode_2","njets","m_vis","mt_1","iso_1"],
               "frac":["QCD","W","TT"]
        },
        "tt":{
            "aiso1": {"vars":["pt_1","pt_2","decayMode_1","njets","m_vis"], 
                      "frac":["QCD","W","TT","DY"]
            },
            "aiso2": {"vars":["pt_2","pt_1","decayMode_2","njets","m_vis"],
                      "frac":["QCD","W","TT","DY"] 
            }
        }
    },
    "uncerts": {

        "et":["ff_qcd_syst_up",
              "ff_qcd_syst_down",
              "ff_qcd_dm0_njet0_stat_up",
              "ff_qcd_dm0_njet0_stat_down",
              "ff_qcd_dm0_njet1_stat_up",
              "ff_qcd_dm0_njet1_stat_down",
              "ff_qcd_dm1_njet0_stat_up",
              "ff_qcd_dm1_njet0_stat_down",
              "ff_qcd_dm1_njet1_stat_up",
              "ff_qcd_dm1_njet1_stat_down",
              "ff_w_syst_up",
              "ff_w_syst_down",
              "ff_w_dm0_njet0_stat_up",
              "ff_w_dm0_njet0_stat_down",
              "ff_w_dm0_njet1_stat_up",
              "ff_w_dm0_njet1_stat_down",
              "ff_w_dm1_njet0_stat_up",
              "ff_w_dm1_njet0_stat_down",
              "ff_w_dm1_njet1_stat_up",
              "ff_w_dm1_njet1_stat_down",
              "ff_tt_syst_up",
              "ff_tt_syst_down",
              "ff_tt_dm0_njet0_stat_up",
              "ff_tt_dm0_njet0_stat_down",
              "ff_tt_dm0_njet1_stat_up",
              "ff_tt_dm0_njet1_stat_down",
              "ff_tt_dm1_njet0_stat_up",
              "ff_tt_dm1_njet0_stat_down",
              "ff_tt_dm1_njet1_stat_up",
              "ff_tt_dm1_njet1_stat_down"
        ],
        "mt":["ff_qcd_syst_up",
              "ff_qcd_syst_down",
              "ff_qcd_dm0_njet0_stat_up",
              "ff_qcd_dm0_njet0_stat_down",
              "ff_qcd_dm0_njet1_stat_up",
              "ff_qcd_dm0_njet1_stat_down",
              "ff_qcd_dm1_njet0_stat_up",
              "ff_qcd_dm1_njet0_stat_down",
              "ff_qcd_dm1_njet1_stat_up",
              "ff_qcd_dm1_njet1_stat_down",
              "ff_w_syst_up",
              "ff_w_syst_down",
              "ff_w_dm0_njet0_stat_up",
              "ff_w_dm0_njet0_stat_down",
              "ff_w_dm0_njet1_stat_up",
              "ff_w_dm0_njet1_stat_down",
              "ff_w_dm1_njet0_stat_up",
              "ff_w_dm1_njet0_stat_down",
              "ff_w_dm1_njet1_stat_up",
              "ff_w_dm1_njet1_stat_down",
              "ff_tt_syst_up",
              "ff_tt_syst_down",
              "ff_tt_dm0_njet0_stat_up",
              "ff_tt_dm0_njet0_stat_down",
              "ff_tt_dm0_njet1_stat_up",
              "ff_tt_dm0_njet1_stat_down",
              "ff_tt_dm1_njet0_stat_up",
              "ff_tt_dm1_njet0_stat_down",
              "ff_tt_dm1_njet1_stat_up",
              "ff_tt_dm1_njet1_stat_down"
        ],
        "tt":["ff_qcd_syst_up",
              "ff_qcd_syst_down",
              "ff_qcd_dm0_njet0_stat_up",
              "ff_qcd_dm0_njet0_stat_down",
              "ff_qcd_dm0_njet1_stat_up",
              "ff_qcd_dm0_njet1_stat_down",
              "ff_qcd_dm1_njet0_stat_up",
              "ff_qcd_dm1_njet0_stat_down",
              "ff_qcd_dm1_njet1_stat_up",
              "ff_qcd_dm1_njet1_stat_down",
              "ff_w_syst_up",
              "ff_w_syst_down",
              "ff_tt_syst_up",
              "ff_tt_syst_down"]
    },
    "uncert_naming": {

        "ff_qcd_syst_up":               "CMS_ff_qcd{channel}_syst_13TeVUp",
        "ff_qcd_syst_down":             "CMS_ff_qcd{channel}_syst_13TeVDown",
        "ff_qcd_dm0_njet0_stat_up":     "CMS_ff_qcd_dm0_njet0{channel}_stat_13TeVUp",
        "ff_qcd_dm0_njet0_stat_down":   "CMS_ff_qcd_dm0_njet0{channel}_stat_13TeVDown",
        "ff_qcd_dm0_njet1_stat_up":     "CMS_ff_qcd_dm0_njet1{channel}_stat_13TeVUp",
        "ff_qcd_dm0_njet1_stat_down":   "CMS_ff_qcd_dm0_njet1{channel}_stat_13TeVDown",
        "ff_qcd_dm1_njet0_stat_up":     "CMS_ff_qcd_dm1_njet0{channel}_stat_13TeVUp",
        "ff_qcd_dm1_njet0_stat_down":   "CMS_ff_qcd_dm1_njet0{channel}_stat_13TeVDown",
        "ff_qcd_dm1_njet1_stat_up":     "CMS_ff_qcd_dm1_njet1{channel}_stat_13TeVUp",
        "ff_qcd_dm1_njet1_stat_down":   "CMS_ff_qcd_dm1_njet1{channel}_stat_13TeVDown",
        "ff_w_syst_up":                 "CMS_ff_w{channel}_syst_13TeVUp",
        "ff_w_syst_down":               "CMS_ff_w{channel}_syst_13TeVDown",
        "ff_w_dm0_njet0_stat_up":       "CMS_ff_w_dm0_njet0{channel}_stat_13TeVUp",
        "ff_w_dm0_njet0_stat_down":     "CMS_ff_w_dm0_njet0{channel}_stat_13TeVDown",
        "ff_w_dm0_njet1_stat_up":       "CMS_ff_w_dm0_njet1{channel}_stat_13TeVUp",
        "ff_w_dm0_njet1_stat_down":     "CMS_ff_w_dm0_njet1{channel}_stat_13TeVDown",
        "ff_w_dm1_njet0_stat_up":       "CMS_ff_w_dm1_njet0{channel}_stat_13TeVUp",
        "ff_w_dm1_njet0_stat_down":     "CMS_ff_w_dm1_njet0{channel}_stat_13TeVDown",
        "ff_w_dm1_njet1_stat_up":       "CMS_ff_w_dm1_njet1{channel}_stat_13TeVUp",
        "ff_w_dm1_njet1_stat_down":     "CMS_ff_w_dm1_njet1{channel}_stat_13TeVDown",
        "ff_tt_syst_up":                "CMS_ff_tt{channel}_syst_13TeVUp",
        "ff_tt_syst_down":              "CMS_ff_tt{channel}_syst_13TeVDown",
        "ff_tt_dm0_njet0_stat_up":      "CMS_ff_tt_dm0_njet0_stat_13TeVUp",
        "ff_tt_dm0_njet0_stat_down":    "CMS_ff_tt_dm0_njet0_stat_13TeVDown",
        "ff_tt_dm0_njet1_stat_up":      "CMS_ff_tt_dm0_njet1_stat_13TeVUp",
        "ff_tt_dm0_njet1_stat_down":    "CMS_ff_tt_dm0_njet1_stat_13TeVDown",
        "ff_tt_dm1_njet0_stat_up":      "CMS_ff_tt_dm1_njet0_stat_13TeVUp",
        "ff_tt_dm1_njet0_stat_down":    "CMS_ff_tt_dm1_njet0_stat_13TeVDown",
        "ff_tt_dm1_njet1_stat_up":      "CMS_ff_tt_dm1_njet1_stat_13TeVUp",
        "ff_tt_dm1_njet1_stat_down":    "CMS_ff_tt_dm1_njet1_stat_13TeVDown"
    }
        
}
